{
  "geometry": {
    "cell_size": {
        "x": 1,
        "y": 1,
        "z": 1
      },
    "number_of_cells": {
      "x": 10,
      "y": 1,
      "z": 5
    },
    "radii": [0.1, 0.1, 0.1],
    "geom_types": ["BCC", "Hybrid1", "Hybrid4"]
  },
    "simulation_parameters": {
      "enable" : true,
      "material": "VeroClear",
      "periodicity": true,
      "DDM": {
        "enable_preconditioner": true,
        "max_iterations": 100,
        "schur_complement_computation": {
          "type": "RBF",
          "precision_greedy": 1e-6
        }
      }
  },
  "boundary_conditions": {
    "Displacement": {
      "Fixed" : {
        "Surface": ["Xmin","Zmin"],
        "DOF": ["X", "Y", "Z", "RX", "RY", "RZ"],
        "Value": [0, 0, 0, 0, 0, 0],
        "SurfaceCells": ["Xmin"]
      },
      "Sym": {
        "Surface": ["Zmax"],
        "DOF": ["Z"],
        "Value": [0]
      }
    },
    "Force": {
      "Load": {
        "Surface": ["Xmax", "Zmax"],
        "DOF": ["X"],
        "Value": [-0.1]
      }
    }
  },
  "optimization_informations": {
      "objective_function": "min",
      "objective_type": "compliance",
      "max_iterations": 50,
      "optimization_parameters": {
        "type": "unit_cell",
        "hybrid": false
      },
      "constraints": {
        "relative_density": {
          "value": 0.3,
          "mode": "eq"
        }
      },
      "enable_parameter_normalization": true,
      "simulation_type": "DDM",
      "enable_gradient_computing": true
  }
}
